fastapi_identity/__init__.py
fastapi_identity/claims.py
fastapi_identity/confirmation.py
fastapi_identity/error_describer.py
fastapi_identity/exc.py
fastapi_identity/http_context.py
fastapi_identity/identity_error.py
fastapi_identity/identity_result.py
fastapi_identity/lookup_normalizer.py
fastapi_identity/options.py
fastapi_identity/password_hasher.py
fastapi_identity/password_validator.py
fastapi_identity/resources.py
fastapi_identity/rfc6238service.py
fastapi_identity/role_manager.py
fastapi_identity/role_validator.py
fastapi_identity/signin_manager.py
fastapi_identity/signin_result.py
fastapi_identity/stores.py
fastapi_identity/token_provider.py
fastapi_identity/types.py
fastapi_identity/user_claims_principal_factory.py
fastapi_identity/user_login_info.py
fastapi_identity/user_manager.py
fastapi_identity/user_validator.py
fastapi_identity/utils.py
fastapi_identity/authentication/__init__.py
fastapi_identity/authentication/base.py
fastapi_identity/authentication/exc.py
fastapi_identity/authentication/middleware.py
fastapi_identity/authentication/types.py
fastapi_identity/authentication/bearer/__init__.py
fastapi_identity/authentication/bearer/backend.py
fastapi_identity/authentication/cookies/__init__.py
fastapi_identity/authentication/cookies/backend.py
fastapi_identity/authorization/__init__.py
fastapi_identity/authorization/authorization_provider.py
fastapi_identity/authorization/base.py
fastapi_identity/authorization/exc.py
fastapi_identity/authorization/handler_context.py
fastapi_identity/authorization/policy_builder.py
fastapi_identity/builders/__init__.py
fastapi_identity/builders/depends.py
fastapi_identity/builders/fastapi_builder.py
fastapi_identity/builders/identity_builder.py
fastapi_identity/builders/service_collection.py
fastapi_identity-1.0.5.dist-info/METADATA
fastapi_identity-1.0.5.dist-info/WHEEL
fastapi_identity-1.0.5.dist-info/top_level.txt
fastapi_identity-1.0.5.dist-info/RECORD
