Metadata-Version: 2.1
Name: fastapi-identity
Version: 1.0.5
Requires-Dist: fastapi
Requires-Dist: pyotp
Requires-Dist: email-validator
Requires-Dist: bcrypt
Requires-Dist: passlib
Requires-Dist: python-jose[cryptography]
Provides-Extra: sqlalchemy
Requires-Dist: fastapi-identity-sqlalchemy ; extra == 'sqlalchemy'
Provides-Extra: tortoise
Requires-Dist: fastapi-identity-tortoise ; extra == 'tortoise'
